{"GBR": ["M 396 295 Q 459.8 175.6 588 134", "United Kingdom", "1701"], "MTQ": ["M 396 295 Q 396.4 294.0 396 293", "Martinique", "1009"], "BRB": ["M 396 295 Q 398.6 295.0 401 298", "Barbados", "966"], "USA": ["M 396 295 Q 356.0 226.8 280 205", "United States of America", "885"], "CAN": ["M 396 295 Q 352.8 182.8 245 131", "Canada", "561"], "VIR": ["M 396 295 Q 392.4 283.4 383 278", "Virgin Islands, U.S.", "455"], "GUY": ["M 396 295 Q 406.2 311.6 403 331", "Guyana", "417"], "TTO": ["M 396 295 Q 392.4 300.8 395 308", "Trinidad and Tobago", "399"], "ANT": ["M 396 295 Q 380.6 292.6 369 302", "Netherlands Antilles", "299"], "GUF": ["M 396 295 Q 416.8 308.8 422 334", "French Guiana", "293"]}