{"NOR": ["M 457 71 Q 550.6 57.8 628 114", "Norway", "3571"], "ITA": ["M 457 71 Q 572.2 92.2 641 187", "Italy", "1102"], "DEU": ["M 457 71 Q 561.0 75.6 634 151", "Germany", "549"], "GTM": ["M 457 71 Q 334.6 147.4 299 288", "Guatemala", "223"], "SCG": ["M 457 71 Q 584.4 81.4 670 178", "Serbia and Montenegro", "101"], "PAK": ["M 457 71 Q 676.0 76.2 831 231", "Pakistan", "51"], "AUS": ["M 457 71 Q 848.6 141.6 1084 464", "Australia", "41"], "ISL": ["M 457 71 Q 501.2 68.2 536 97", "Iceland", "39"], "KWT": ["M 457 71 Q 640.0 92.8 758 236", "Kuwait", "25"], "ISR": ["M 457 71 Q 617.6 98.2 716 229", "Israel", "20"]}